markdown_markup_emoji/__init__.py
markdown_markup_emoji/markup_emoji.py
markdown_markup_emoji-0.2.2.dist-info/LICENSE
markdown_markup_emoji-0.2.2.dist-info/METADATA
markdown_markup_emoji-0.2.2.dist-info/WHEEL
markdown_markup_emoji-0.2.2.dist-info/entry_points.txt
markdown_markup_emoji-0.2.2.dist-info/top_level.txt
markdown_markup_emoji-0.2.2.dist-info/RECORD
