Metadata-Version: 2.1
Name: markdown-markup-emoji
Version: 0.2.2
Summary: Python markdown extension for markup Emoji
Home-page: https://github.com/EloiseSeverin/markdown_markup_emoji/
Author: Eloise Severin
Author-email: Eloise.severin @ gmail.com
License: MIT
Keywords: Markdown,extension,plugin,Emoji
Platform: UNKNOWN
Classifier: Intended Audience :: Developers
Classifier: Topic :: Software Development :: Build Tools
Classifier: License :: OSI Approved :: MIT License
Classifier: Programming Language :: Python :: 3
Requires-Dist: Markdown (>=3.0.0)
